indoxGen_torch/__init__.py
indoxGen_torch/GAN/__init__.py
indoxGen_torch/GAN/classifier.py
indoxGen_torch/GAN/config.py
indoxGen_torch/GAN/data_transformer.py
indoxGen_torch/GAN/discriminator.py
indoxGen_torch/GAN/evaluation.py
indoxGen_torch/GAN/gan.py
indoxGen_torch/GAN/generator.py
indoxGen_torch/GAN/tabular_gan.py
indoxGen_torch/GAN/utils.py
indoxGen_torch-0.0.9.dist-info/LICENSE
indoxGen_torch-0.0.9.dist-info/METADATA
indoxGen_torch-0.0.9.dist-info/WHEEL
indoxGen_torch-0.0.9.dist-info/top_level.txt
indoxGen_torch-0.0.9.dist-info/RECORD
