Metadata-Version: 2.1
Name: indoxGen-torch
Version: 0.0.9
Summary: Indox Synthetic Data Generation (GAN-pytorch)
Home-page: https://github.com/osllmai/IndoxGen/tree/master/libs/indoxGen_torch
Author: nerdstudio
Author-email: ashkan@nematifamilyfundation.onmicrosoft.com
License: AGPL-3.0-or-later
Keywords: AI,deep learning,language models,synthetic data generation,machine learning,NLP
Classifier: Development Status :: 3 - Alpha
Classifier: Intended Audience :: Developers
Classifier: Topic :: Software Development :: Build Tools
Classifier: License :: OSI Approved :: GNU Affero General Public License v3 or later (AGPLv3+)
Classifier: Programming Language :: Python :: 3.9
Classifier: Programming Language :: Python :: 3.10
Classifier: Programming Language :: Python :: 3.11
Classifier: Programming Language :: Python :: 3.12
Requires-Python: >=3.9
License-File: LICENSE
Requires-Dist: dython ==0.7.8
Requires-Dist: matplotlib ==3.8.4
Requires-Dist: numpy ==1.24.4
Requires-Dist: pandas ==2.2.2
Requires-Dist: scikit-learn ==1.4.2
Requires-Dist: scipy ==1.13.1
Requires-Dist: seaborn ==0.13.2
Requires-Dist: setuptools ==69.5.1
Requires-Dist: torch ==2.4.1
